cpin.py
io.py
pycpt-0.0.1.dist-info/LICENSE
pycpt-0.0.1.dist-info/METADATA
pycpt-0.0.1.dist-info/WHEEL
pycpt-0.0.1.dist-info/top_level.txt
pycpt-0.0.1.dist-info/RECORD
